datasets/__init__.py
datasets/adult/__init__.py
datasets/winequality/__init__.py
synthpop/__init__.py
synthpop/synthpop.py
synthpop/method/__init__.py
synthpop/method/base.py
synthpop/method/cart.py
synthpop/method/empty.py
synthpop/method/helpers.py
synthpop/method/norm.py
synthpop/method/normrank.py
synthpop/method/polyreg.py
synthpop/method/sample.py
synthpop/processor/__init__.py
synthpop/processor/processor.py
synthpop/validator/__init__.py
synthpop/validator/validator.py
py_synthpop-0.1.2.dist-info/LICENSE
py_synthpop-0.1.2.dist-info/METADATA
py_synthpop-0.1.2.dist-info/WHEEL
py_synthpop-0.1.2.dist-info/top_level.txt
py_synthpop-0.1.2.dist-info/RECORD
