Metadata-Version: 2.1
Name: py-synthpop
Version: 0.1.2
Summary: Python implementation of the R package synthpop
Home-page: https://github.com/hazy/synthpop
Author: Georgi Ganev, Sofiane Mahiou
Author-email: info@hazy.com
License: UNKNOWN
Platform: UNKNOWN
Classifier: Programming Language :: Python :: 3
Classifier: License :: OSI Approved :: MIT License
Classifier: Operating System :: OS Independent
Requires-Python: >=3.6
